{
  "version": 3,
  "middleware": {
    "/": {
      "files": [
        "server/edge-runtime-webpack.js",
        "server/src/middleware.js"
      ],
      "name": "src/middleware",
      "page": "/",
      "matchers": [
        {
          "regexp": "^(?:\\/(_next\\/data\\/[^/]{1,}))?(?:\\/((?!api|_next\\/static|_next\\/image|.*\\.png$).*))(\\.json)?[\\/#\\?]?$",
          "originalSource": "/((?!api|_next/static|_next/image|.*\\.png$).*)"
        }
      ],
      "wasm": [],
      "assets": [],
      "env": {
        "__NEXT_BUILD_ID": "WKTJvD8JFisTBltdHjG9q",
        "NEXT_SERVER_ACTIONS_ENCRYPTION_KEY": "vLdMteKNDsOSDKC/WiQnZxo7B/BS4XoZMjuI2O5JSoc=",
        "__NEXT_PREVIEW_MODE_ID": "bfe2bab567b70f87900f0a0879f4775c",
        "__NEXT_PREVIEW_MODE_ENCRYPTION_KEY": "68a071ae9935c96bd9d66c62ad846b1719214764ca540825e9286a593cd20661",
        "__NEXT_PREVIEW_MODE_SIGNING_KEY": "c8ae522fedcc6f2121b5f946d9ef12143a1ee1aad19a175e9caff6b257aa9941"
      }
    }
  },
  "functions": {},
  "sortedMiddleware": [
    "/"
  ]
}